dj_importmap-1.0.0.dist-info/licenses/LICENSE
importmap/__init__.py
importmap/apps.py
importmap/base.py
importmap/context_processors.py
importmap/templatetags/__init__.py
importmap/templatetags/importmap.py
dj_importmap-1.0.0.dist-info/METADATA
dj_importmap-1.0.0.dist-info/WHEEL
dj_importmap-1.0.0.dist-info/top_level.txt
dj_importmap-1.0.0.dist-info/RECORD
