Metadata-Version: 2.4
Name: dj-importmap
Version: 1.0.0
Summary: Integrate HTML importmaps with Django for modern web development
Author-email: Christophe Henry <contact@c-henry.fr>
Project-URL: Homepage, https://github.com/betagouv/dj-importmap
Project-URL: Documentation, https://github.com/betagouv/dj-importmap/blob/main/README.md
Project-URL: Repository, https://github.com/betagouv/dj-importmap
Project-URL: Issues, https://github.com/betagouv/dj-importmap/issues
Project-URL: Changelog, https://github.com/betagouv/dj-importmap/blob/main/CHANGELOG.md
Classifier: Development Status :: 5 - Production/Stable
Classifier: Environment :: Plugins
Classifier: Environment :: Web Environment
Classifier: Framework :: Django
Classifier: Framework :: Django :: 4.2
Classifier: Framework :: Django :: 5.0
Classifier: Framework :: Django :: 5.1
Classifier: Framework :: Django :: 5.2
Classifier: Programming Language :: Python :: 3.10
Classifier: Programming Language :: Python :: 3.11
Classifier: Programming Language :: Python :: 3.12
Classifier: Programming Language :: Python :: 3.13
Classifier: Programming Language :: Python :: 3.14
Requires-Python: >=3.10
License-File: LICENSE
Requires-Dist: django>=4.2
Provides-Extra: dev
Requires-Dist: pre-commit; extra == "dev"
Requires-Dist: uv; extra == "dev"
Requires-Dist: ruff; extra == "dev"
Dynamic: license-file
